gym_update/__init__.py
gym_update/envs/__init__.py
gym_update/envs/check.py
gym_update/envs/doc2_0.py
gym_update/envs/doc2_0_V1.py
gym_update/envs/doc2_0bandit.py
gym_update/envs/update_env.py
gym_update/envs/update_env1.py
gym_update-0.6.2.dist-info/LICENSE
gym_update-0.6.2.dist-info/METADATA
gym_update-0.6.2.dist-info/WHEEL
gym_update-0.6.2.dist-info/top_level.txt
gym_update-0.6.2.dist-info/RECORD
