Metadata-Version: 2.1
Name: gym-update
Version: 0.6.2
Summary: A OpenAI Gym Env for continuous control
Home-page: UNKNOWN
Author: Claudia Viaro
License: MIT
Platform: UNKNOWN
License-File: LICENSE
Requires-Dist: gym
